flink_scrat/__init__.py
flink_scrat/exceptions.py
flink_scrat/job_manager_connector.py
flink_scrat/main.py
flink_scrat/utils.py
flink_scrat-0.3.6.dist-info/LICENSE
flink_scrat-0.3.6.dist-info/METADATA
flink_scrat-0.3.6.dist-info/WHEEL
flink_scrat-0.3.6.dist-info/entry_points.txt
flink_scrat-0.3.6.dist-info/top_level.txt
flink_scrat-0.3.6.dist-info/RECORD
