Metadata-Version: 2.1
Name: flink-scrat
Version: 0.3.6
Summary: Python client to deploy flink applications to remote clusters via the flink cluster API
Home-page: https://github.com/Cobliteam/flink-scrat
Author: Nicolau Tahan
Author-email: tech@cobli.co
License: MIT
Download-URL: https://github.com/Cobliteam/flink-scrat/archive/0.3.6.tar.gz
Keywords: flink deploy emr aws
Platform: UNKNOWN
Requires-Dist: requests (==2.22.0)
Requires-Dist: argparse (==1.4.0)
Requires-Dist: pyaml (==19.4.1)
Requires-Dist: PyYAML (==5.1.1)
Requires-Dist: envparse (==0.2.0)
